yeecli/__init__.py
yeecli/cli.py
yeecli-0.2.0.dist-info/AUTHORS.rst
yeecli-0.2.0.dist-info/LICENSE
yeecli-0.2.0.dist-info/METADATA
yeecli-0.2.0.dist-info/WHEEL
yeecli-0.2.0.dist-info/entry_points.txt
yeecli-0.2.0.dist-info/top_level.txt
yeecli-0.2.0.dist-info/RECORD
