Metadata-Version: 2.1
Name: yeecli
Version: 0.2.0
Summary: yeecli is a command-line utility for controlling the YeeLight RGB LED lightbulb.
Home-page: https://github.com/skorokithakis/yeecli
Author: Stavros Korokithakis
Author-email: hi@stavros.io
License: BSD
Keywords: yeelight xiaomi led rgb yeecli
Platform: UNKNOWN
Classifier: Development Status :: 2 - Pre-Alpha
Classifier: Intended Audience :: End Users/Desktop
Classifier: License :: OSI Approved :: BSD License
Classifier: Natural Language :: English
Classifier: Programming Language :: Python :: 3
Classifier: Programming Language :: Python :: 3.3
Classifier: Programming Language :: Python :: 3.4
Classifier: Programming Language :: Python :: 3.5
Requires-Dist: click (>=6.6)
Requires-Dist: yeelight (>=0.3.0)
